{
 "running": true,
 "mode": "full",
 "phase": "YUL->NCE 2026-11-23",
 "checksDone": 6654,
 "checksPlanned": 41488,
 "percent": 16,
 "dealsFound": 3014,
 "updatedAt": "2026-07-15T10:37:07",
 "publishedAt": "2026-07-15T14:37:56.035325+00:00",
 "queuedCount": 3,
 "queued": [
  {
   "label": "round trip (EU ⇄ asia, 12-21 nights)",
   "mode": "quick"
  },
  {
   "label": "round trip (EU ⇄ middle_east, 12-21 nights)",
   "mode": "quick"
  },
  {
   "label": "round trip (EU ⇄ africa, 12-21 nights)",
   "mode": "quick"
  }
 ],
 "totalDeals": 7015
}